rtl/sync_fifo.v
// ============================================================================
// Module      : sync_fifo
// Description : Parameterized synchronous FIFO with full/empty flags and
//               overflow/underflow protection. Single clock domain.
// Author      : N C Shobha
// ============================================================================

module sync_fifo #(
    parameter DATA_WIDTH = 8,
    parameter DEPTH      = 16,                       // must be power of 2
    parameter ADDR_WIDTH = $clog2(DEPTH)
) (
    input  wire                    clk,
    input  wire                    rst_n,     // active-low synchronous reset

    // Write port
    input  wire                    wr_en,
    input  wire [DATA_WIDTH-1:0]   wr_data,
    output wire                    full,
    output wire                    almost_full,

    // Read port
    input  wire                    rd_en,
    output reg  [DATA_WIDTH-1:0]   rd_data,
    output wire                    empty,
    output wire                    almost_empty,

    // Status
    output wire [ADDR_WIDTH:0]     count,     // current occupancy (0..DEPTH)
    output reg                     overflow,  // pulses when wr attempted while full
    output reg                     underflow  // pulses when rd attempted while empty
);

    // Memory array
    reg [DATA_WIDTH-1:0] mem [0:DEPTH-1];

    // Pointers are ADDR_WIDTH+1 bits wide: MSB is a wrap bit used to
    // distinguish full from empty when read_ptr == write_ptr.
    reg [ADDR_WIDTH:0] wr_ptr, rd_ptr;

    wire [ADDR_WIDTH-1:0] wr_addr = wr_ptr[ADDR_WIDTH-1:0];
    wire [ADDR_WIDTH-1:0] rd_addr = rd_ptr[ADDR_WIDTH-1:0];

    assign empty = (wr_ptr == rd_ptr);
    assign full  = (wr_ptr[ADDR_WIDTH] != rd_ptr[ADDR_WIDTH]) &&
                   (wr_ptr[ADDR_WIDTH-1:0] == rd_ptr[ADDR_WIDTH-1:0]);

    assign count = wr_ptr - rd_ptr;
    assign almost_full  = (count == DEPTH-1);
    assign almost_empty = (count == 1);

    wire wr_valid = wr_en && !full;
    wire rd_valid = rd_en && !empty;

    // Write logic
    always @(posedge clk) begin
        if (!rst_n) begin
            wr_ptr <= 0;
        end else if (wr_valid) begin
            mem[wr_addr] <= wr_data;
            wr_ptr <= wr_ptr + 1'b1;
        end
    end

    // Read logic
    always @(posedge clk) begin
        if (!rst_n) begin
            rd_ptr  <= 0;
            rd_data <= {DATA_WIDTH{1'b0}};
        end else if (rd_valid) begin
            rd_data <= mem[rd_addr];
            rd_ptr  <= rd_ptr + 1'b1;
        end
    end

    // Overflow / underflow detection (protection: writes/reads are
    // dropped, but we flag the illegal attempt for verification/debug)
    always @(posedge clk) begin
        if (!rst_n) begin
            overflow  <= 1'b0;
            underflow <= 1'b0;
        end else begin
            overflow  <= wr_en && full;
            underflow <= rd_en && empty;
        end
    end

    // ------------------------------------------------------------------
    // Assertions - immediate assertions checked every clock edge.
    // (Icarus Verilog's open-source simulator supports immediate
    // assertions; full concurrent SVA `property`/`assert property` is
    // used in commercial tools like QuestaSim/VCS - the same checks
    // are expressed here in a portable style.)
    // ------------------------------------------------------------------
    // synthesis translate_off
    always @(posedge clk) begin
        if (rst_n) begin
            assert (!(wr_en && full) || (count == DEPTH))
                else $error("[ASSERTION FAILED] Write accepted while FIFO full at time %0t", $time);

            assert (!(rd_en && empty) || (count == 0))
                else $error("[ASSERTION FAILED] Read accepted while FIFO empty at time %0t", $time);

            assert (count <= DEPTH)
                else $error("[ASSERTION FAILED] FIFO count out of range at time %0t", $time);

            assert (!(full && empty))
                else $error("[ASSERTION FAILED] full and empty asserted simultaneously at time %0t", $time);
        end
    end
    // synthesis translate_on

endmodule

tb/tb_sync_fifo.v
// ============================================================================
// Testbench    : tb_sync_fifo
// Description  : Self-checking, constrained-random verification environment
//                for sync_fifo. Includes:
//                  - Randomized write/read stimulus generation
//                  - Reference model (array-based circular buffer, mirrors
//                    DUT semantics) + scoreboard comparison
//                  - Directed corner-case tests (full, empty, simultaneous
//                    read/write, back-to-back bursts)
//                  - Functional coverage tracking (bins for corner cases)
//                  - Assertion checks live in the RTL (sync_fifo.v)
// Author       : N C Shobha
// ============================================================================
`timescale 1ns/1ps

module tb_sync_fifo;

    localparam DATA_WIDTH = 8;
    localparam DEPTH      = 16;
    localparam ADDR_WIDTH = $clog2(DEPTH);
    localparam NUM_RANDOM_TXNS = 2000;
    localparam REF_SIZE = 4096; // generous reference-model capacity

    reg                     clk;
    reg                     rst_n;
    reg                     wr_en;
    reg  [DATA_WIDTH-1:0]   wr_data;
    wire                    full, almost_full;
    reg                     rd_en;
    wire [DATA_WIDTH-1:0]   rd_data;
    wire                    empty, almost_empty;
    wire [ADDR_WIDTH:0]     count;
    wire                    overflow, underflow;

    // ---- DUT instantiation ----
    sync_fifo #(
        .DATA_WIDTH(DATA_WIDTH),
        .DEPTH(DEPTH)
    ) dut (
        .clk(clk), .rst_n(rst_n),
        .wr_en(wr_en), .wr_data(wr_data), .full(full), .almost_full(almost_full),
        .rd_en(rd_en), .rd_data(rd_data), .empty(empty), .almost_empty(almost_empty),
        .count(count), .overflow(overflow), .underflow(underflow)
    );

    // ---- Clock generation: 10ns period (100MHz) ----
    initial clk = 0;
    always #5 clk = ~clk;

    // ---- Reference model: plain array-based circular buffer, mirrors
    //      expected FIFO content independently of the DUT's internals ----
    reg [DATA_WIDTH-1:0] ref_mem [0:REF_SIZE-1];
    integer ref_head;   // next element to be read
    integer ref_tail;   // next free slot to write
    integer ref_count;  // number of valid elements currently queued

    task automatic ref_push(input [DATA_WIDTH-1:0] d);
        begin
            ref_mem[ref_tail] = d;
            ref_tail = (ref_tail + 1) % REF_SIZE;
            ref_count = ref_count + 1;
        end
    endtask

    task automatic ref_pop(output [DATA_WIDTH-1:0] d);
        begin
            d = ref_mem[ref_head];
            ref_head = (ref_head + 1) % REF_SIZE;
            ref_count = ref_count - 1;
        end
    endtask

    // ---- Scoreboard counters ----
    integer total_checks       = 0;
    integer total_errors       = 0;
    integer writes_accepted    = 0;
    integer reads_accepted     = 0;
    integer overflow_events    = 0;
    integer underflow_events   = 0;

    // ---- Coverage bins (corner cases) ----
    integer cov_hit_full            = 0;
    integer cov_hit_empty           = 0;
    integer cov_hit_almost_full     = 0;
    integer cov_hit_almost_empty    = 0;
    integer cov_hit_simul_rw        = 0;   // simultaneous read+write, not full/empty
    integer cov_hit_simul_rw_full   = 0;   // simultaneous read+write while full
    integer cov_hit_wr_reject       = 0;   // write attempted while full (rejected)
    integer cov_hit_rd_reject       = 0;   // read attempted while empty (rejected)
    integer cov_hit_back_to_back_wr = 0;   // >=4 consecutive writes
    integer cov_hit_back_to_back_rd = 0;   // >=4 consecutive reads
    integer consec_wr = 0, consec_rd = 0;

    // ---- Latency-correct data check bookkeeping ----
    // rd_data is registered (1-cycle latency after rd_en), so we predict
    // the expected value BEFORE driving a read, then compare it against
    // rd_data on the following cycle.
    reg [DATA_WIDTH-1:0] cmp_val;
    reg                  cmp_pending;

    reg                  do_wr, do_rd;
    reg [DATA_WIDTH-1:0] rnd_data;
    integer              i;
    reg                  wr_accept, rd_accept;

    // ---- Task: reset DUT and reference model ----
    task automatic apply_reset;
        begin
            rst_n       = 0;
            wr_en       = 0;
            rd_en       = 0;
            wr_data     = 0;
            ref_head    = 0;
            ref_tail    = 0;
            ref_count   = 0;
            cmp_pending = 0;
            repeat (3) @(posedge clk);
            rst_n = 1;
            @(posedge clk);
            #1;
        end
    endtask

    // ---- Task: single-cycle drive ----
    task automatic drive_cycle(input do_write, input do_read, input [DATA_WIDTH-1:0] data);
        begin
            wr_en   = do_write;
            wr_data = data;
            rd_en   = do_read;
            @(posedge clk);
            #1; // let NBA updates (wr_ptr/rd_ptr/rd_data) settle before
                // any code samples full/empty/rd_data/count this cycle
        end
    endtask

    // ---- Scoreboard: takes PRE-EDGE accept decisions explicitly, so it
    //      never re-derives full/empty from post-edge (already-updated)
    //      DUT signals - avoiding a classic race condition where full/empty
    //      changes on the very edge a read/write is issued. ----
    task automatic check_and_score(input wr_accept, input rd_accept, input wr_attempt, input rd_attempt);
        reg [DATA_WIDTH-1:0] dummy;
        begin
            if (wr_accept) begin
                ref_push(wr_data);
                writes_accepted = writes_accepted + 1;
            end
            if (wr_attempt && !wr_accept) begin
                overflow_events = overflow_events + 1;
                cov_hit_wr_reject = cov_hit_wr_reject + 1;
            end

            if (rd_accept) begin
                ref_pop(dummy);
                reads_accepted = reads_accepted + 1;
                total_checks   = total_checks + 1;
            end
            if (rd_attempt && !rd_accept) begin
                underflow_events = underflow_events + 1;
                cov_hit_rd_reject = cov_hit_rd_reject + 1;
            end

            // Coverage bin tracking (post-edge flags are fine here - just
            // observational, not used to drive scoreboard state)
            if (full)          cov_hit_full          = cov_hit_full + 1;
            if (empty)         cov_hit_empty         = cov_hit_empty + 1;
            if (almost_full)   cov_hit_almost_full   = cov_hit_almost_full + 1;
            if (almost_empty)  cov_hit_almost_empty  = cov_hit_almost_empty + 1;
            if (wr_attempt && rd_attempt) begin
                if (!wr_accept && rd_accept) cov_hit_simul_rw_full = cov_hit_simul_rw_full + 1; // write rejected (full) while read succeeds
                else                         cov_hit_simul_rw      = cov_hit_simul_rw + 1;
            end

            if (wr_accept) consec_wr = consec_wr + 1; else consec_wr = 0;
            if (rd_accept) consec_rd = consec_rd + 1; else consec_rd = 0;
            if (consec_wr >= 4) cov_hit_back_to_back_wr = cov_hit_back_to_back_wr + 1;
            if (consec_rd >= 4) cov_hit_back_to_back_rd = cov_hit_back_to_back_rd + 1;
        end
    endtask

    task automatic report_coverage_bin(input [8*40-1:0] name, input integer hits);
        begin
            if (hits > 0)
                $display("  [HIT ] %0s : %0d hits", name, hits);
            else
                $display("  [MISS] %0s : %0d hits", name, hits);
        end
    endtask

    // ---- Main stimulus ----
    initial begin
        $display("=========================================================");
        $display(" Synchronous FIFO Verification - Constrained Random Test ");
        $display(" DEPTH=%0d  DATA_WIDTH=%0d  NUM_RANDOM_TXNS=%0d", DEPTH, DATA_WIDTH, NUM_RANDOM_TXNS);
        $display("=========================================================");

        apply_reset();

        // ---------------- Directed corner-case tests ----------------
        $display("[TEST] Directed: Fill FIFO completely, verify FULL flag");
        for (i = 0; i < DEPTH; i = i + 1) begin
            wr_accept = !full; rd_accept = 0;
            drive_cycle(1, 0, i[DATA_WIDTH-1:0]);
            check_and_score(wr_accept, rd_accept, 1, 0);
        end
        if (!full) begin
            $display("  ERROR: Expected FULL after %0d writes, full=%0b", DEPTH, full);
            total_errors = total_errors + 1;
        end else $display("  PASS: FIFO correctly reports FULL after %0d writes", DEPTH);

        $display("[TEST] Directed: Attempt write while FULL (should be rejected)");
        wr_accept = !full; rd_accept = 0;
        drive_cycle(1, 0, 8'hFF);
        check_and_score(wr_accept, rd_accept, 1, 0);
        if (!overflow) begin
            $display("  ERROR: Expected overflow flag on write-while-full");
            total_errors = total_errors + 1;
        end else $display("  PASS: overflow flag correctly asserted");

        $display("[TEST] Directed: Drain FIFO completely, verify EMPTY flag");
        for (i = 0; i < DEPTH; i = i + 1) begin
            wr_accept = 0; rd_accept = !empty;
            drive_cycle(0, 1, 0);
            check_and_score(wr_accept, rd_accept, 0, 1);
        end
        if (!empty) begin
            $display("  ERROR: Expected EMPTY after draining, empty=%0b", empty);
            total_errors = total_errors + 1;
        end else $display("  PASS: FIFO correctly reports EMPTY after full drain");

        $display("[TEST] Directed: Attempt read while EMPTY (should be rejected)");
        wr_accept = 0; rd_accept = !empty;
        drive_cycle(0, 1, 0);
        check_and_score(wr_accept, rd_accept, 0, 1);
        if (!underflow) begin
            $display("  ERROR: Expected underflow flag on read-while-empty");
            total_errors = total_errors + 1;
        end else $display("  PASS: underflow flag correctly asserted");

        $display("[TEST] Directed: Simultaneous read+write in steady state");
        for (i = 0; i < 4; i = i + 1) begin
            wr_accept = !full; rd_accept = 0;
            drive_cycle(1, 0, i[DATA_WIDTH-1:0]);
            check_and_score(wr_accept, rd_accept, 1, 0);
        end
        for (i = 0; i < 8; i = i + 1) begin
            wr_accept = !full; rd_accept = !empty;
            drive_cycle(1, 1, (100+i));
            check_and_score(wr_accept, rd_accept, 1, 1);
        end
        $display("  PASS: simultaneous read/write cycles executed");

        $display("[TEST] Directed: Simultaneous read+write while FULL");
        for (i = 0; i < DEPTH; i = i + 1) begin
            wr_accept = !full; rd_accept = 0;
            drive_cycle(1, 0, (200+i));
            check_and_score(wr_accept, rd_accept, 1, 0);
        end
        for (i = 0; i < 6; i = i + 1) begin
            wr_accept = !full; rd_accept = !empty;
            drive_cycle(1, 1, (220+i));
            check_and_score(wr_accept, rd_accept, 1, 1);
        end
        $display("  PASS: simultaneous read/write while full cycles executed");

        apply_reset();

        // ---------------- Constrained-random stimulus ----------------
        $display("[TEST] Constrained-random: %0d cycles of randomized wr_en/rd_en/data", NUM_RANDOM_TXNS);
        for (i = 0; i < NUM_RANDOM_TXNS; i = i + 1) begin
            do_wr    = ($urandom_range(0,99) < 55);  // 55% write probability
            do_rd    = ($urandom_range(0,99) < 55);  // 55% read probability
            rnd_data = $urandom_range(0,255);

            // Data-integrity check for the PREVIOUS cycle's registered read
            if (cmp_pending) begin
                if (rd_data !== cmp_val) begin
                    $display("  ERROR @%0t: rd_data mismatch. Expected=%0h Got=%0h", $time, cmp_val, rd_data);
                    total_errors = total_errors + 1;
                end
            end

            // Capture PRE-EDGE accept decisions once, using current
            // (pre-edge) full/empty - reused for BOTH the read prediction
            // and the scoreboard push/pop, so they can never disagree.
            wr_accept = do_wr && !full;
            rd_accept = do_rd && !empty;

            // Predict THIS cycle's read result before driving (peek, don't pop yet)
            if (rd_accept) begin
                cmp_val     = ref_mem[ref_head];
                cmp_pending = 1;
            end else begin
                cmp_pending = 0;
            end

            drive_cycle(do_wr, do_rd, rnd_data);
            check_and_score(wr_accept, rd_accept, do_wr, do_rd);
        end

        // Flush final pending comparison
        if (cmp_pending) begin
            if (rd_data !== cmp_val) begin
                $display("  ERROR @%0t: rd_data mismatch (final). Expected=%0h Got=%0h", $time, cmp_val, rd_data);
                total_errors = total_errors + 1;
            end
        end

        $display("[INFO] Entries remaining in reference model at end of test: %0d", ref_count);

        $display("=========================================================");
        $display(" FUNCTIONAL COVERAGE REPORT");
        $display("=========================================================");
        report_coverage_bin("FULL condition hit",                cov_hit_full);
        report_coverage_bin("EMPTY condition hit",                cov_hit_empty);
        report_coverage_bin("ALMOST_FULL condition hit",          cov_hit_almost_full);
        report_coverage_bin("ALMOST_EMPTY condition hit",         cov_hit_almost_empty);
        report_coverage_bin("Simultaneous R+W (steady state)",    cov_hit_simul_rw);
        report_coverage_bin("Simul. R+W, write rejected (FULL)", cov_hit_simul_rw_full);
        report_coverage_bin("Write rejected (overflow attempt)",  cov_hit_wr_reject);
        report_coverage_bin("Read rejected (underflow attempt)",  cov_hit_rd_reject);
        report_coverage_bin("Back-to-back writes (>=4 consec.)",  cov_hit_back_to_back_wr);
        report_coverage_bin("Back-to-back reads (>=4 consec.)",   cov_hit_back_to_back_rd);

        begin
            integer bins_hit;
            bins_hit = (cov_hit_full>0) + (cov_hit_empty>0) + (cov_hit_almost_full>0) +
                       (cov_hit_almost_empty>0) + (cov_hit_simul_rw>0) + (cov_hit_simul_rw_full>0) +
                       (cov_hit_wr_reject>0) + (cov_hit_rd_reject>0) + (cov_hit_back_to_back_wr>0) +
                       (cov_hit_back_to_back_rd>0);
            $display("---------------------------------------------------------");
            $display(" Coverage bins hit: %0d / 10  (%0.1f%%)", bins_hit, (bins_hit*100.0)/10.0);
        end

        $display("=========================================================");
        $display(" SCOREBOARD SUMMARY");
        $display("=========================================================");
        $display(" Total data checks performed   : %0d", total_checks);
        $display(" Writes accepted                : %0d", writes_accepted);
        $display(" Reads accepted                 : %0d", reads_accepted);
        $display(" Overflow (rejected write) evts : %0d", overflow_events);
        $display(" Underflow (rejected read) evts : %0d", underflow_events);
        $display(" TOTAL ERRORS                   : %0d", total_errors);
        if (total_errors == 0)
            $display(" RESULT: *** ALL CHECKS PASSED ***");
        else
            $display(" RESULT: *** %0d CHECK(S) FAILED ***", total_errors);
        $display("=========================================================");

        $finish;
    end

    // Waveform dump
    initial begin
        $dumpfile("sync_fifo.vcd");
        $dumpvars(0, tb_sync_fifo);
    end

endmodule

sync_fifo.vcd
$date
	Wed Aug 12 09:30:58 2026
$end
$version
	Icarus Verilog
$end
$timescale
	1ps
$end
$scope module tb_sync_fifo $end
$var wire 1 ! underflow $end
$var wire 8 " rd_data [7:0] $end
$var wire 1 # overflow $end
$var wire 1 $ full $end
$var wire 1 % empty $end
$var wire 5 & count [4:0] $end
$var wire 1 ' almost_full $end
$var wire 1 ( almost_empty $end
$var parameter 32 ) ADDR_WIDTH $end
$var parameter 32 * DATA_WIDTH $end
$var parameter 32 + DEPTH $end
$var parameter 32 , NUM_RANDOM_TXNS $end
$var parameter 32 - REF_SIZE $end
$var reg 1 . clk $end
$var reg 1 / cmp_pending $end
$var reg 8 0 cmp_val [7:0] $end
$var reg 1 1 do_rd $end
$var reg 1 2 do_wr $end
$var reg 1 3 rd_accept $end
$var reg 1 4 rd_en $end
$var reg 8 5 rnd_data [7:0] $end
$var reg 1 6 rst_n $end
$var reg 1 7 wr_accept $end
$var reg 8 8 wr_data [7:0] $end
$var reg 1 9 wr_en $end
$var integer 32 : consec_rd [31:0] $end
$var integer 32 ; consec_wr [31:0] $end
$var integer 32 < cov_hit_almost_empty [31:0] $end
$var integer 32 = cov_hit_almost_full [31:0] $end
$var integer 32 > cov_hit_back_to_back_rd [31:0] $end
$var integer 32 ? cov_hit_back_to_back_wr [31:0] $end
$var integer 32 @ cov_hit_empty [31:0] $end
$var integer 32 A cov_hit_full [31:0] $end
$var integer 32 B cov_hit_rd_reject [31:0] $end
$var integer 32 C cov_hit_simul_rw [31:0] $end
$var integer 32 D cov_hit_simul_rw_full [31:0] $end
$var integer 32 E cov_hit_wr_reject [31:0] $end
$var integer 32 F i [31:0] $end
$var integer 32 G overflow_events [31:0] $end
$var integer 32 H reads_accepted [31:0] $end
$var integer 32 I ref_count [31:0] $end
$var integer 32 J ref_head [31:0] $end
$var integer 32 K ref_tail [31:0] $end
$var integer 32 L total_checks [31:0] $end
$var integer 32 M total_errors [31:0] $end
$var integer 32 N underflow_events [31:0] $end
$var integer 32 O writes_accepted [31:0] $end
$scope module dut $end
$var wire 1 . clk $end
$var wire 1 $ full $end
$var wire 1 4 rd_en $end
$var wire 1 P rd_valid $end
$var wire 1 6 rst_n $end
$var wire 8 Q wr_data [7:0] $end
$var wire 1 9 wr_en $end
$var wire 1 R wr_valid $end
$var wire 4 S wr_addr [3:0] $end
$var wire 4 T rd_addr [3:0] $end
$var wire 1 % empty $end
$var wire 5 U count [4:0] $end
$var wire 1 ' almost_full $end
$var wire 1 ( almost_empty $end
$var parameter 32 V ADDR_WIDTH $end
$var parameter 32 W DATA_WIDTH $end
$var parameter 32 X DEPTH $end
$var reg 1 # overflow $end
$var reg 8 Y rd_data [7:0] $end
$var reg 5 Z rd_ptr [4:0] $end
$var reg 1 ! underflow $end
$var reg 5 [ wr_ptr [4:0] $end
$upscope $end
$scope begin $unm_blk_41 $end
$var integer 32 \ bins_hit [31:0] $end
$upscope $end
$scope task apply_reset $end
$upscope $end
$scope task check_and_score $end
$upscope $end
$scope task drive_cycle $end
$upscope $end
$scope task ref_pop $end
$upscope $end
$scope task ref_push $end
$upscope $end
$scope task report_coverage_bin $end
$upscope $end
$upscope $end
$enddefinitions $end
$comment Show the parameter values. $end
$dumpall
b10000 X
b1000 W
b100 V
b1000000000000 -
b11111010000 ,
b10000 +
b1000 *
b100 )
$end
#0
$dumpvars
bx \
bx [
bx Z
bx Y
bx U
bx T
bx S
0R
b0 Q
0P
b0 O
b0 N
b0 M
b0 L
b0 K
b0 J
b0 I
b0 H
b0 G
bx F
b0 E
b0 D
b0 C
b0 B
b0 A
b0 @
b0 ?
b0 >
b0 =
b0 <
b0 ;
b0 :
09
b0 8
x7
06
bx 5
04
x3
x2
x1
bx 0
0/
0.
x(
x'
bx &
x%
x$
x#
bx "
x!
$end
#5000
0$
b0 S
b0 T
1%
0'
0(
b0 &
b0 U
b0 [
b0 "
b0 Y
b0 Z
0!
0#
1.
#10000
0.
#15000
1.
#20000
0.
#25000
16
1.
#30000
0.
#35000
1.
#36000
1R
19
03
17
b0 F
#40000
0.
#45000
b1 S
0%
1(
b1 &
b1 U
b1 [
1.
#46000
b1 8
b1 Q
b1 F
b1 ;
b1 <
b1 O
b1 I
b1 K
#50000
0.
#55000
b10 S
0(
b10 &
b10 U
b10 [
1.
#56000
b10 8
b10 Q
b10 F
b10 ;
b10 O
b10 I
b10 K
#60000
0.
#65000
b11 S
b11 &
b11 U
b11 [
1.
#66000
b11 8
b11 Q
b11 F
b11 ;
b11 O
b11 I
b11 K
#70000
0.
#75000
b100 S
b100 &
b100 U
b100 [
1.
#76000
b100 8
b100 Q
b100 F
b1 ?
b100 ;
b100 O
b100 I
b100 K
#80000
0.
#85000
b101 S
b101 &
b101 U
b101 [
1.
#86000
b101 8
b101 Q
b101 F
b10 ?
b101 ;
b101 O
b101 I
b101 K
#90000
0.
#95000
b110 S
b110 &
b110 U
b110 [
1.
#96000
b110 8
b110 Q
b110 F
b11 ?
b110 ;
b110 O
b110 I
b110 K
#100000
0.
#105000
b111 S
b111 &
b111 U
b111 [
1.
#106000
b111 8
b111 Q
b111 F
b100 ?
b111 ;
b111 O
b111 I
b111 K
#110000
0.
#115000
b1000 S
b1000 &
b1000 U
b1000 [
1.
#116000
b1000 8
b1000 Q
b1000 F
b101 ?
b1000 ;
b1000 O
b1000 I
b1000 K
#120000
0.
#125000
b1001 S
b1001 &
b1001 U
b1001 [
1.
#126000
b1001 8
b1001 Q
b1001 F
b110 ?
b1001 ;
b1001 O
b1001 I
b1001 K
#130000
0.
#135000
b1010 S
b1010 &
b1010 U
b1010 [
1.
#136000
b1010 8
b1010 Q
b1010 F
b111 ?
b1010 ;
b1010 O
b1010 I
b1010 K
#140000
0.
#145000
b1011 S
b1011 &
b1011 U
b1011 [
1.
#146000
b1011 8
b1011 Q
b1011 F
b1000 ?
b1011 ;
b1011 O
b1011 I
b1011 K
#150000
0.
#155000
b1100 S
b1100 &
b1100 U
b1100 [
1.
#156000
b1100 8
b1100 Q
b1100 F
b1001 ?
b1100 ;
b1100 O
b1100 I
b1100 K
#160000
0.
#165000
b1101 S
b1101 &
b1101 U
b1101 [
1.
#166000
b1101 8
b1101 Q
b1101 F
b1010 ?
b1101 ;
b1101 O
b1101 I
b1101 K
#170000
0.
#175000
b1110 S
b1110 &
b1110 U
b1110 [
1.
#176000
b1110 8
b1110 Q
b1110 F
b1011 ?
b1110 ;
b1110 O
b1110 I
b1110 K
#180000
0.
#185000
b1111 S
1'
b1111 &
b1111 U
b1111 [
1.
#186000
b1111 8
b1111 Q
b1111 F
b1100 ?
b1111 ;
b1 =
b1111 O
b1111 I
b1111 K
#190000
0.
#195000
0R
1$
b0 S
0'
b10000 &
b10000 U
b10000 [
1.
#196000
b11111111 8
b11111111 Q
07
b10000 F
b1101 ?
b10000 ;
b1 A
b10000 O
b10000 I
b10000 K
#200000
0.
#205000
1#
1.
#206000
1P
14
b0 8
b0 Q
09
13
b0 F
b0 ;
b10 A
b1 E
b1 G
#210000
0.
#215000
0$
b1 T
0#
1'
b1111 &
b1111 U
b1 Z
1.
#216000
b1 F
b1 :
b10 =
b1 L
b1 H
b1111 I
b1 J
#220000
0.
#225000
b10 T
0'
b1110 &
b1110 U
b10 Z
b1 "
b1 Y
1.
#226000
b10 F
b10 :
b10 L
b10 H
b1110 I
b10 J
#230000
0.
#235000
b11 T
b1101 &
b1101 U
b11 Z
b10 "
b10 Y
1.
#236000
b11 F
b11 :
b11 L
b11 H
b1101 I
b11 J
#240000
0.
#245000
b100 T
b1100 &
b1100 U
b100 Z
b11 "
b11 Y
1.
#246000
b100 F
b1 >
b100 :
b100 L
b100 H
b1100 I
b100 J
#250000
0.
#255000
b101 T
b1011 &
b1011 U
b101 Z
b100 "
b100 Y
1.
#256000
b101 F
b10 >
b101 :
b101 L
b101 H
b1011 I
b101 J
#260000
0.
#265000
b110 T
b1010 &
b1010 U
b110 Z
b101 "
b101 Y
1.
#266000
b110 F
b11 >
b110 :
b110 L
b110 H
b1010 I
b110 J
#270000
0.
#275000
b111 T
b1001 &
b1001 U
b111 Z
b110 "
b110 Y
1.
#276000
b111 F
b100 >
b111 :
b111 L
b111 H
b1001 I
b111 J
#280000
0.
#285000
b1000 T
b1000 &
b1000 U
b1000 Z
b111 "
b111 Y
1.
#286000
b1000 F
b101 >
b1000 :
b1000 L
b1000 H
b1000 I
b1000 J
#290000
0.
#295000
b1001 T
b111 &
b111 U
b1001 Z
b1000 "
b1000 Y
1.
#296000
b1001 F
b110 >
b1001 :
b1001 L
b1001 H
b111 I
b1001 J
#300000
0.
#305000
b1010 T
b110 &
b110 U
b1010 Z
b1001 "
b1001 Y
1.
#306000
b1010 F
b111 >
b1010 :
b1010 L
b1010 H
b110 I
b1010 J
#310000
0.
#315000
b1011 T
b101 &
b101 U
b1011 Z
b1010 "
b1010 Y
1.
#316000
b1011 F
b1000 >
b1011 :
b1011 L
b1011 H
b101 I
b1011 J
#320000
0.
#325000
b1100 T
b100 &
b100 U
b1100 Z
b1011 "
b1011 Y
1.
#326000
b1100 F
b1001 >
b1100 :
b1100 L
b1100 H
b100 I
b1100 J
#330000
0.
#335000
b1101 T
b11 &
b11 U
b1101 Z
b1100 "
b1100 Y
1.
#336000
b1101 F
b1010 >
b1101 :
b1101 L
b1101 H
b11 I
b1101 J
#340000
0.
#345000
b1110 T
b10 &
b10 U
b1110 Z
b1101 "
b1101 Y
1.
#346000
b1110 F
b1011 >
b1110 :
b1110 L
b1110 H
b10 I
b1110 J
#350000
0.
#355000
b1111 T
1(
b1 &
b1 U
b1111 Z
b1110 "
b1110 Y
1.
#356000
b1111 F
b1100 >
b1111 :
b10 <
b1111 L
b1111 H
b1 I
b1111 J
#360000
0.
#365000
0$
b0 T
0P
1%
0(
b0 &
b0 U
b10000 Z
b1111 "
b1111 Y
1.
#366000
03
b10000 F
b1101 >
b10000 :
b1 @
b10000 L
b10000 H
b0 I
b10000 J
#370000
0.
#375000
1!
1.
#376000
1R
04
19
17
b0 F
b0 :
b10 @
b1 B
b1 N
#380000
0.
#385000
b1 S
0%
1(
b1 &
b1 U
b10001 [
0!
1.
#386000
b1 8
b1 Q
b1 F
b1 ;
b11 <
b10001 O
b1 I
b10001 K
#390000
0.
#395000
b10 S
0(
b10 &
b10 U
b10010 [
1.
#396000
b10 8
b10 Q
b10 F
b10 ;
b10010 O
b10 I
b10010 K
#400000
0.
#405000
b11 S
b11 &
b11 U
b10011 [
1.
#406000
b11 8
b11 Q
b11 F
b11 ;
b10011 O
b11 I
b10011 K
#410000
0.
#415000
b100 S
b100 &
b100 U
b10100 [
1.
#416000
1P
14
b1100100 8
b1100100 Q
13
b0 F
b1110 ?
b100 ;
b10100 O
b100 I
b10100 K
#420000
0.
#425000
b101 S
b1 T
b10101 [
b100 &
b100 U
b10001 Z
b0 "
b0 Y
1.
#426000
b1100101 8
b1100101 Q
b1 F
b1111 ?
b1 :
b101 ;
b1 C
b10001 L
b10001 H
b10001 J
b10101 O
b100 I
b10101 K
#430000
0.
#435000
b10 T
b110 S
b10010 Z
b1 "
b1 Y
b100 &
b100 U
b10110 [
1.
#436000
b1100110 8
b1100110 Q
b10 F
b10000 ?
b10 :
b110 ;
b10 C
b10010 L
b10010 H
b10010 J
b10110 O
b100 I
b10110 K
#440000
0.
#445000
b111 S
b11 T
b10111 [
b100 &
b100 U
b10011 Z
b10 "
b10 Y
1.
#446000
b1100111 8
b1100111 Q
b11 F
b10001 ?
b11 :
b111 ;
b11 C
b10011 L
b10011 H
b10011 J
b10111 O
b100 I
b10111 K
#450000
0.
#455000
b100 T
b1000 S
b10100 Z
b11 "
b11 Y
b100 &
b100 U
b11000 [
1.
#456000
b1101000 8
b1101000 Q
b100 F
b1110 >
b10010 ?
b100 :
b1000 ;
b100 C
b10100 L
b10100 H
b10100 J
b11000 O
b100 I
b11000 K
#460000
0.
#465000
b1001 S
b101 T
b11001 [
b100 &
b100 U
b10101 Z
b1100100 "
b1100100 Y
1.
#466000
b1101001 8
b1101001 Q
b101 F
b1111 >
b10011 ?
b101 :
b1001 ;
b101 C
b10101 L
b10101 H
b10101 J
b11001 O
b100 I
b11001 K
#470000
0.
#475000
b110 T
b1010 S
b10110 Z
b1100101 "
b1100101 Y
b100 &
b100 U
b11010 [
1.
#476000
b1101010 8
b1101010 Q
b110 F
b10000 >
b10100 ?
b110 :
b1010 ;
b110 C
b10110 L
b10110 H
b10110 J
b11010 O
b100 I
b11010 K
#480000
0.
#485000
b1011 S
b111 T
b11011 [
b100 &
b100 U
b10111 Z
b1100110 "
b1100110 Y
1.
#486000
b1101011 8
b1101011 Q
b111 F
b10001 >
b10101 ?
b111 :
b1011 ;
b111 C
b10111 L
b10111 H
b10111 J
b11011 O
b100 I
b11011 K
#490000
0.
#495000
b1000 T
b1100 S
b11000 Z
b1100111 "
b1100111 Y
b100 &
b100 U
b11100 [
1.
#496000
0P
04
b11001000 8
b11001000 Q
03
b0 F
b10010 >
b10110 ?
b1000 :
b1100 ;
b1000 C
b11000 L
b11000 H
b11000 J
b11100 O
b100 I
b11100 K
#500000
0.
#505000
b1101 S
b101 &
b101 U
b11101 [
1.
#506000
b11001001 8
b11001001 Q
b1 F
b10111 ?
b0 :
b1101 ;
b11101 O
b101 I
b11101 K
#510000
0.
#515000
b1110 S
b110 &
b110 U
b11110 [
1.
#516000
b11001010 8
b11001010 Q
b10 F
b11000 ?
b1110 ;
b11110 O
b110 I
b11110 K
#520000
0.
#525000
b1111 S
b111 &
b111 U
b11111 [
1.
#526000
b11001011 8
b11001011 Q
b11 F
b11001 ?
b1111 ;
b11111 O
b111 I
b11111 K
#530000
0.
#535000
b0 S
b1000 &
b1000 U
b0 [
1.
